{
  "pools": [
    {
      "rolls": 1,
      "entries": [
        {
          "type": "minecraft:item",
          "name": "minecraft:carrot",
          "functions": [
            {
              "function": "minecraft:set_name",
              "name": {
                "text": "Live-Attenuated Vaccine",
                "color": "#0f6407",
                "italic": false
              }
            },
            {
              "function": "minecraft:set_lore",
              "lore": [
                {
                  "text": "Right-Click to use",
                  "color": "yellow",
                  "italic": false
                },
                {
                  "text": " "
                },
                {
                  "text": "Injects a weak virus into a teammate, inflicting slowness, weakness, and nausea for 4s."
                },
                {
                  "text": "After the debuffs expire, the teammate becomes immune to them as well as armor reduction for the rest of the current life."
                },
                {
                  "text": "Has a max range of 2 blocks."
                }
              ],
              "mode": "insert"
            },
            {
              "function": "minecraft:set_components",
              "components": {
                "minecraft:custom_model_data": {
                  "floats": [
                    204
                  ]
                },
                "consumable": {
                  "consume_seconds": 1000000
                },
                "minecraft:food": {
                  "nutrition": 0,
                  "saturation": 0,
                  "can_always_eat": true
                }
              }
            },
            {
              "function": "minecraft:set_custom_data",
              "tag": "{vaccine:1b}"
            }
          ]
        }
      ]
    }
  ]
}
